passwdgen/__init__.py
passwdgen/__main__.py
passwdgen/cmdline.py
passwdgen/constants.py
passwdgen/generator.py
passwdgen/utils.py
passwdgen/data/default-word-list.txt
passwdgen-0.4.0.dist-info/entry_points.txt
passwdgen-0.4.0.dist-info/LICENSE
passwdgen-0.4.0.dist-info/WHEEL
passwdgen-0.4.0.dist-info/METADATA
passwdgen-0.4.0.dist-info/RECORD
