Metadata-Version: 2.1
Name: passwdgen
Version: 0.4.0
Summary: A password generation utility
Author-email: Thane Thomson <connect@thanethomson.com>
Requires-Python: >=3.9
Classifier: Development Status :: 4 - Beta
Classifier: Environment :: Console
Classifier: Intended Audience :: Developers
Classifier: License :: OSI Approved :: MIT License
Classifier: Natural Language :: English
Classifier: Operating System :: POSIX
Classifier: Operating System :: MacOS
Classifier: Programming Language :: Python :: 3.6
Classifier: Programming Language :: Python :: 3.7
Classifier: Topic :: Utilities
Requires-Dist: pyperclip >= 1.8.2
Project-URL: Homepage, https://github.com/thanethomson/passwdgen
